fdc_sdk/__init__.py
fdc_sdk/fw_client.py
fdc_sdk/test.py
fdc_sdk-0.0.4.dist-info/METADATA
fdc_sdk-0.0.4.dist-info/WHEEL
fdc_sdk-0.0.4.dist-info/top_level.txt
fdc_sdk-0.0.4.dist-info/RECORD
