Metadata-Version: 2.4
Name: fdc_sdk
Version: 0.0.4
Summary: sdk for factweavers datacloud
Author-email: Ansar cs <ansar.cs@dbizsolution.com>
Classifier: Programming Language :: Python :: 3
Classifier: License :: OSI Approved :: MIT License
Classifier: Operating System :: OS Independent
Requires-Python: >=3.7
